{"updated_at":"2026-06-29T22:12:55+09:00","items":{"360750":{"ticker":"360750","name":"","last_close":null,"daily_change_pct":null},"379800":{"ticker":"379800","name":"","last_close":null,"daily_change_pct":null},"360200":{"ticker":"360200","name":"","last_close":null,"daily_change_pct":null},"433330":{"ticker":"433330","name":"","last_close":null,"daily_change_pct":null},"133690":{"ticker":"133690","name":"","last_close":null,"daily_change_pct":null},"458730":{"ticker":"458730","name":"","last_close":null,"daily_change_pct":null},"482730":{"ticker":"482730","name":"","last_close":null,"daily_change_pct":null},"474220":{"ticker":"474220","name":"","last_close":null,"daily_change_pct":null},"069500":{"ticker":"069500","name":"","last_close":null,"daily_change_pct":null},"365780":{"ticker":"365780","name":"","last_close":null,"daily_change_pct":null}}}